{
  "session_name": "full_ecommerce_b381-382_20250810_155518",
  "completed_urls": [
    "https://ciciban.rs/",
    "https://ciello.com.br/",
    "https://cinema.mu/",
    "https://cigarro.pl/",
    "https://chudo-ostriv.com.ua/",
    "https://cigarrspecialisten.se/",
    "https://cigadesign.com/",
    "https://cigarpassion.ch/",
    "https://circehoupijamas.com.ar/",
    "https://cielitostore.com/",
    "https://cicinia.fr/",
    "https://cigarcountry.com/",
    "https://chubbycable.com/",
    "https://cinders.ie/",
    "https://cinepacks.store/",
    "https://cipta-diklat-pertiwi-noc.com/",
    "https://ciclidrigani.it/",
    "https://chromeworld.jp/",
    "https://cicana.co/",
    "https://cipo-eshop.hu/",
    "https://ciglissime.com/",
    "https://ciechocinek.pl/",
    "https://cigarchief.com/",
    "https://christydawn.com/",
    "https://cicloscorredor.com/",
    "https://cigarsdaily.com/",
    "https://ciode.es/",
    "https://cilek.com/",
    "https://circle.melonbooks.co.jp/",
    "https://cigslt.io/",
    "https://ciaotutti.nl/",
    "https://cidef.cl/",
    "https://chucheriaspr.com/",
    "https://cicilya.co.il/",
    "https://cincopunto7.com/",
    "https://cilekkonsept.com/",
    "https://chromeindustries.com/",
    "https://churchsource.com/",
    "https://chronicguru.com/",
    "https://christusmuguerza.com.mx/",
    "https://chronos.mg/",
    "https://ci-puiyye.com/",
    "https://circadia.com/",
    "https://cilek.gr/",
    "https://cigarman.co.kr/",
    "https://cicinails.hr/"
  ],
  "failed_urls": [
    "https://chuckanddons.com/",
    "https://cisurfboards.com/",
    "https://cigartehrann.com/",
    "https://cigarretetabacaria.com/"
  ],
  "current_batch": 2,
  "total_batches": 2,
  "batch_size": 25,
  "start_time": 1754841318.8722968,
  "last_updated": 1754842429.4064965,
  "total_completed": 46,
  "total_failed": 4,
  "completion_percentage": 100.0
}